{
    "users": [
        {
    
            "name": "Sabrina Sawayn",
            "id": "2",
            "email": "tuyenpv23281@gmail.com2"
        },
        {
            "name": "Brandon Legros",
            "id": "3",
            "email": "tuyenpv23281@gmail.com3"
        },
        {
            "name": "Myrtle Grady",
            "id": "4",
            "email": "tuyenpv23281@gmail.com1"
        },
        {
            "name": "Lorraine Bins",
            "id": "5",
            "email": "tuyenpv23281@gmail.com"
        },
        {
            "name": "Doris Effertz IV",
            "id": "6",
            "email": "tuyenpv23281@gmail.com"
        },
        {
            "name": "Lloyd Spencer",
            "id": "7",
            "email": "tuyenpv23281@gmail.com"
        },
        {
            "name": "Lonnie Tromp",
            "id": "8",
            "email": "tuyenpv23281@gmail.com"
        }
        
    ]
    
}